esix/__init__.py
esix/api.py
esix/comment.py
esix/config.py
esix/errors.py
esix/forum.py
esix/pool.py
esix/post.py
esix/tag.py
esix/takedown.py
esix/ticket.py
esix/user.py
esix-1.3.1.dist-info/DESCRIPTION.rst
esix-1.3.1.dist-info/METADATA
esix-1.3.1.dist-info/RECORD
esix-1.3.1.dist-info/WHEEL
esix-1.3.1.dist-info/metadata.json
esix-1.3.1.dist-info/top_level.txt
