Metadata-Version: 1.0
Name: esix
Version: 1.3.1
Summary: High level frontend for the e621 JSON API.
Home-page: https://bitbucket.org/AMV_Ph34r/python-esix
Author: Alex Schaeffer
Author-email: AMVPh34r@gmail.com
License: MIT
Platform: UNKNOWN
